README.txt
setup.py
PageCalc.egg-info/PKG-INFO
PageCalc.egg-info/SOURCES.txt
PageCalc.egg-info/dependency_links.txt
PageCalc.egg-info/top_level.txt
pagecalc/__init__.py
pagecalc/test.py
pagecalc/example/app.py
pagecalc/example/index.html
pagecalc/example/paginator.html