Metadata-Version: 1.1
Name: PageCalc
Version: 0.2.2
Summary: Python pagination calculator
Home-page: https://bitbucket.org/saaj/pagecalc
Author: saaj
Author-email: mail@saaj.me
License: LGPL-2.1+
Platform: Any
Classifier: Topic :: Software Development :: Libraries
Classifier: Programming Language :: Python :: 2.7
Classifier: Programming Language :: Python :: 3.3
Classifier: Intended Audience :: Developers
